{
  "project_info": {
    "project_number": "35627898276",
    "project_id": "yesco-a11f7",
    "storage_bucket": "yesco-a11f7.appspot.com"
  },
  "client": [
    {
      "client_info": {
        "mobilesdk_app_id": "1:35627898276:android:640f8336028d9ac3931d31",
        "android_client_info": {
          "package_name": "kr.co.yesco"
        }
      },
      "oauth_client": [
        {
          "client_id": "35627898276-jgc7649k2lmis1vctjpfrofs4hq5fqus.apps.googleusercontent.com",
          "client_type": 3
        }
      ],
      "api_key": [
        {
          "current_key": "AIzaSyBg7XeJkhZYzzm6t3XKgLzNYOynmaNWjo8"
        }
      ],
      "services": {
        "appinvite_service": {
          "other_platform_oauth_client": [
            {
              "client_id": "35627898276-jgc7649k2lmis1vctjpfrofs4hq5fqus.apps.googleusercontent.com",
              "client_type": 3
            }
          ]
        }
      }
    }
  ],
  "configuration_version": "1"
}